MANIFEST.in
README.md
setup.py
actionviews/__init__.py
actionviews/base.py
actionviews/decorators.py
actionviews/exceptions.py
django_actionviews.egg-info/PKG-INFO
django_actionviews.egg-info/SOURCES.txt
django_actionviews.egg-info/dependency_links.txt
django_actionviews.egg-info/requires.txt
django_actionviews.egg-info/top_level.txt