Metadata-Version: 1.1
Name: django-actionviews
Version: 0.2.1
Summary: Alternative Class Based Views for Django
Home-page: https://github.com/lig/django-actionviews
Author: Serge Matveenko
Author-email: s@matveenko.ru
License: Apache
Keywords: django generic views
Platform: UNKNOWN
Classifier: Development Status :: 4 - Beta
Classifier: Intended Audience :: Developers
Classifier: License :: OSI Approved :: Apache Software License
Classifier: Programming Language :: Python :: 3
Classifier: Topic :: Database
Classifier: Framework :: Django
